{"stats":{"minecraft:broken":{"minecraft:golden_boots":5,"minecraft:diamond_helmet":1,"minecraft:iron_boots":3,"minecraft:iron_chestplate":3,"minecraft:iron_leggings":2,"minecraft:golden_leggings":1,"minecraft:stone_pickaxe":5,"minecraft:iron_sword":1,"minecraft:fishing_rod":1,"minecraft:golden_chestplate":2,"minecraft:chainmail_leggings":1,"minecraft:shield":3,"minecraft:iron_pickaxe":2,"minecraft:iron_helmet":3},"minecraft:killed_by":{"minecraft:zombie_villager":2,"minecraft:zombified_piglin":1,"minecraft:wither_skeleton":12,"minecraft:creeper":8,"minecraft:drowned":4,"minecraft:piglin":1,"minecraft:cave_spider":2,"minecraft:blaze":3,"minecraft:zombie":11,"minecraft:player":1,"minecraft:enderman":1,"minecraft:iron_golem":1,"minecraft:hoglin":1,"minecraft:skeleton":13,"minecraft:guardian":2,"minecraft:phantom":1},"minecraft:dropped":{"minecraft:dirt":6,"minecraft:iron_pickaxe":1,"minecraft:bone":8,"minecraft:emerald_block":11,"minecraft:carrot":6,"minecraft:trident":1,"minecraft:chainmail_boots":1,"minecraft:arrow":1,"minecraft:netherrack":4,"minecraft:cobblestone":7,"minecraft:string":4,"minecraft:diamond_sword":2,"minecraft:spider_eye":5,"minecraft:stone_bricks":5,"minecraft:bow":1,"minecraft:stone_pickaxe":1},"minecraft:custom":{"minecraft:animals_bred":4,"minecraft:interact_with_crafting_table":131,"minecraft:open_barrel":138,"minecraft:bell_ring":23,"minecraft:leave_game":11,"minecraft:time_since_death":32151,"minecraft:damage_resisted":836,"minecraft:sprint_one_cm":3197646,"minecraft:damage_blocked_by_shield":9130,"minecraft:drop":64,"minecraft:talked_to_villager":131,"minecraft:deaths":96,"minecraft:jump":15652,"minecraft:interact_with_brewingstand":23,"minecraft:walk_on_water_one_cm":511759,"minecraft:enchant_item":19,"minecraft:interact_with_furnace":102,"minecraft:traded_with_villager":366,"minecraft:interact_with_cartography_table":1,"minecraft:play_one_minute":1214871,"minecraft:interact_with_loom":3,"minecraft:sleep_in_bed":8,"minecraft:open_enderchest":101,"minecraft:damage_dealt":166010,"minecraft:player_kills":8,"minecraft:crouch_one_cm":116943,"minecraft:interact_with_smoker":10,"minecraft:horse_one_cm":63861,"minecraft:interact_with_smithing_table":2,"minecraft:mob_kills":1138,"minecraft:interact_with_anvil":8,"minecraft:inspect_hopper":13,"minecraft:climb_one_cm":122730,"minecraft:walk_one_cm":2667293,"minecraft:sneak_time":65997,"minecraft:walk_under_water_one_cm":706861,"minecraft:boat_one_cm":1854891,"minecraft:interact_with_blast_furnace":6,"minecraft:interact_with_grindstone":7,"minecraft:time_since_rest":32177,"minecraft:damage_taken":52187,"minecraft:swim_one_cm":1449597,"minecraft:fly_one_cm":3182394,"minecraft:open_chest":526,"minecraft:fall_one_cm":411470},"minecraft:crafted":{"minecraft:grindstone":1,"minecraft:oak_planks":192,"minecraft:smooth_stone":4,"minecraft:dark_oak_boat":18,"minecraft:blaze_powder":14,"minecraft:loom":1,"minecraft:stone":8,"minecraft:diamond_shovel":1,"minecraft:glass":64,"minecraft:iron_boots":4,"minecraft:chest":2,"minecraft:stone_bricks":4,"minecraft:golden_boots":1,"minecraft:glass_bottle":12,"minecraft:emerald":340,"minecraft:diamond_axe":1,"minecraft:crafting_table":11,"minecraft:spruce_planks":96,"minecraft:wooden_pickaxe":1,"minecraft:iron_helmet":4,"minecraft:brewing_stand":2,"minecraft:iron_chestplate":4,"minecraft:book":10,"minecraft:diamond_pickaxe":1,"minecraft:paper":30,"minecraft:golden_leggings":1,"minecraft:emerald_block":11,"minecraft:shield":4,"minecraft:stick":104,"minecraft:stone_slab":6,"minecraft:iron_pickaxe":4,"minecraft:compass":1,"minecraft:iron_ingot":124,"minecraft:gold_ingot":45,"minecraft:shears":1,"minecraft:redstone":16,"minecraft:fishing_rod":7,"minecraft:golden_chestplate":1,"minecraft:experience_bottle":48,"minecraft:furnace":6,"minecraft:blast_furnace":1,"minecraft:dark_oak_sign":3,"minecraft:flint_and_steel":1,"minecraft:dark_oak_fence":33,"minecraft:iron_hoe":1,"minecraft:ender_pearl":31,"minecraft:stone_pickaxe":8,"minecraft:dark_oak_planks":208,"minecraft:cooked_cod":10,"minecraft:diamond_sword":1,"minecraft:iron_sword":6,"minecraft:bucket":1,"minecraft:glowstone":16,"minecraft:air":0,"minecraft:oak_boat":49,"minecraft:golden_apple":4,"minecraft:fermented_spider_eye":4,"minecraft:wooden_axe":1,"minecraft:iron_leggings":5,"minecraft:white_bed":1,"minecraft:torch":88,"minecraft:lapis_lazuli":22},"minecraft:used":{"minecraft:chest":3,"minecraft:shield":206,"minecraft:iron_sword":932,"minecraft:nether_wart":50,"minecraft:bell":1,"minecraft:soul_sand":38,"minecraft:nether_bricks":1,"minecraft:carrot":487,"minecraft:milk_bucket":1,"minecraft:stone_bricks":1,"minecraft:bow":145,"minecraft:dark_oak_boat":13,"minecraft:sweet_berries":18,"minecraft:furnace":7,"minecraft:oak_sapling":5,"minecraft:cooked_cod":282,"minecraft:egg":66,"minecraft:diorite":5,"minecraft:wither_skeleton_skull":2,"minecraft:stone_pickaxe":884,"minecraft:dark_oak_sign":1,"minecraft:powered_rail":5,"minecraft:oak_planks":47,"minecraft:ender_pearl":14,"minecraft:wooden_pickaxe":5,"minecraft:sugar_cane":6,"minecraft:diamond_axe":527,"minecraft:sand":3,"minecraft:loom":1,"minecraft:blast_furnace":2,"minecraft:redstone_torch":3,"minecraft:melon_slice":7,"minecraft:gravel":2,"minecraft:diamond_sword":1168,"minecraft:grindstone":6,"minecraft:dark_oak_fence":35,"minecraft:andesite":1,"minecraft:oak_boat":7,"minecraft:experience_bottle":48,"minecraft:oak_fence":1,"minecraft:trident":33,"minecraft:tropical_fish":4,"minecraft:spruce_planks":11,"minecraft:netherrack":409,"minecraft:torch":44,"minecraft:brewing_stand":7,"minecraft:dirt":482,"minecraft:iron_hoe":131,"minecraft:dark_oak_planks":6,"minecraft:wooden_axe":7,"minecraft:glowstone":8,"minecraft:soul_soil":10,"minecraft:minecart":1,"minecraft:wheat_seeds":26,"minecraft:water_bucket":100,"minecraft:glass_bottle":13,"minecraft:baked_potato":81,"minecraft:rail":2,"minecraft:oak_slab":2,"minecraft:crafting_table":14,"minecraft:red_bed":1,"minecraft:white_bed":7,"minecraft:cod":1,"minecraft:diamond_pickaxe":15,"minecraft:activator_rail":11,"minecraft:diamond_shovel":677,"minecraft:iron_pickaxe":960,"minecraft:fishing_rod":112,"minecraft:cobblestone":424,"minecraft:potion":1,"minecraft:bucket":101,"minecraft:sea_pickle":4,"minecraft:splash_potion":5,"minecraft:smooth_stone":1},"minecraft:killed":{"minecraft:cave_spider":453,"minecraft:zombified_piglin":1,"minecraft:spider":58,"minecraft:pufferfish":1,"minecraft:skeleton":73,"minecraft:guardian":2,"minecraft:tropical_fish":12,"minecraft:magma_cube":7,"minecraft:piglin":5,"minecraft:zombie_villager":2,"minecraft:iron_golem":1,"minecraft:creeper":38,"minecraft:trader_llama":2,"minecraft:pillager":2,"minecraft:zombie":178,"minecraft:ghast":2,"minecraft:blaze":18,"minecraft:cow":4,"minecraft:phantom":6,"minecraft:horse":2,"minecraft:drowned":221,"minecraft:wandering_trader":1,"minecraft:hoglin":4,"minecraft:wither_skeleton":28,"minecraft:enderman":2},"minecraft:picked_up":{"minecraft:wheat":5,"minecraft:chainmail_boots":1,"minecraft:prismarine_shard":6,"minecraft:lead":2,"minecraft:diamond_sword":2,"minecraft:potion":4,"minecraft:enchanted_book":1,"minecraft:nether_brick":5,"minecraft:brewing_stand":5,"minecraft:string":29,"minecraft:soul_soil":23,"minecraft:pufferfish":1,"minecraft:activator_rail":2,"minecraft:sea_pickle":4,"minecraft:gold_nugget":162,"minecraft:spruce_planks":34,"minecraft:redstone_torch":1,"minecraft:iron_pickaxe":1,"minecraft:melon_slice":7,"minecraft:furnace":3,"minecraft:golden_helmet":2,"minecraft:stick":79,"minecraft:oak_fence":1,"minecraft:torch":33,"minecraft:diorite":5,"minecraft:golden_chestplate":4,"minecraft:rotten_flesh":425,"minecraft:tropical_fish":14,"minecraft:netherite_chestplate":1,"minecraft:blaze_rod":9,"minecraft:obsidian":10,"minecraft:cod":14,"minecraft:cobblestone":278,"minecraft:magma_block":2,"minecraft:andesite":6,"minecraft:dark_oak_boat":7,"minecraft:golden_leggings":2,"minecraft:potato":6,"minecraft:flint":1,"minecraft:netherite_leggings":1,"minecraft:wither_skeleton_skull":5,"minecraft:lapis_lazuli":90,"minecraft:dirt":252,"minecraft:leather_boots":1,"minecraft:bone":105,"minecraft:bow":5,"minecraft:wheat_seeds":19,"minecraft:grindstone":7,"minecraft:powered_rail":1,"minecraft:oak_planks":5,"minecraft:sand":139,"minecraft:loom":1,"minecraft:spectral_arrow":23,"minecraft:dark_oak_log":26,"minecraft:diamond":12,"minecraft:granite":1,"minecraft:bone_meal":1,"minecraft:oak_sapling":8,"minecraft:netherrack":686,"minecraft:dark_oak_fence":2,"minecraft:crimson_roots":1,"minecraft:fishing_rod":2,"minecraft:crafting_table":4,"minecraft:azure_bluet":1,"minecraft:splash_potion":8,"minecraft:nether_wart":52,"minecraft:clay_ball":24,"minecraft:brown_mushroom":13,"minecraft:gold_block":2,"minecraft:red_bed":1,"minecraft:iron_shovel":2,"minecraft:blackstone":112,"minecraft:beef":6,"minecraft:oak_boat":4,"minecraft:minecart":2,"minecraft:sugar_cane":81,"minecraft:chest":2,"minecraft:phantom_membrane":3,"minecraft:egg":65,"minecraft:fire_charge":3,"minecraft:trident":3,"minecraft:carrot":378,"minecraft:redstone":118,"minecraft:dark_oak_planks":2,"minecraft:arrow":44,"minecraft:weeping_vines":2,"minecraft:diamond_chestplate":1,"minecraft:nether_bricks":1,"minecraft:gold_ingot":8,"minecraft:white_wool":20,"minecraft:oxeye_daisy":1,"minecraft:basalt":140,"minecraft:leather":10,"minecraft:golden_boots":5,"minecraft:gunpowder":39,"minecraft:apple":4,"minecraft:stone_bricks":6,"minecraft:kelp":6,"minecraft:iron_ingot":13,"minecraft:iron_ore":193,"minecraft:iron_sword":1,"minecraft:soul_sand":38,"minecraft:oak_slab":2,"minecraft:warped_fungus":2,"minecraft:emerald_block":11,"minecraft:sweet_berries":17,"minecraft:gravel":15,"minecraft:blast_furnace":1,"minecraft:white_bed":2,"minecraft:spruce_log":24,"minecraft:gold_ore":37,"minecraft:crying_obsidian":3,"minecraft:spider_eye":14,"minecraft:leather_helmet":3,"minecraft:coal":321,"minecraft:ender_pearl":2},"minecraft:mined":{"minecraft:spruce_planks":3,"minecraft:white_bed":2,"minecraft:obsidian":10,"minecraft:brewing_stand":5,"minecraft:granite":1,"minecraft:grass_block":54,"minecraft:soul_soil":22,"minecraft:composter":3,"minecraft:nether_wart":22,"minecraft:weeping_vines_plant":1,"minecraft:tall_seagrass":5,"minecraft:magma_block":2,"minecraft:iron_ore":191,"minecraft:fire":5,"minecraft:red_bed":2,"minecraft:blackstone":99,"minecraft:kelp_plant":8,"minecraft:crimson_nylium":1,"minecraft:clay":12,"minecraft:torch":8,"minecraft:blast_furnace":1,"minecraft:melon":1,"minecraft:chest":1,"minecraft:mushroom_stem":4,"minecraft:cobblestone":32,"minecraft:grindstone":7,"minecraft:sugar_cane":35,"minecraft:oak_planks":5,"minecraft:wall_torch":2,"minecraft:seagrass":178,"minecraft:powered_rail":1,"minecraft:wheat":3,"minecraft:lilac":1,"minecraft:activator_rail":2,"minecraft:warped_fungus":2,"minecraft:grass":15,"minecraft:loom":1,"minecraft:sand":208,"minecraft:dirt":367,"minecraft:wither_skeleton_skull":2,"minecraft:netherrack":701,"minecraft:oak_leaves":507,"minecraft:nether_gold_ore":41,"minecraft:diamond_ore":12,"minecraft:dark_oak_log":31,"minecraft:nether_bricks":1,"minecraft:dark_oak_fence":2,"minecraft:crimson_roots":1,"minecraft:weeping_vines":1,"minecraft:brown_mushroom_block":45,"minecraft:spruce_leaves":3,"minecraft:kelp":3,"minecraft:redstone_ore":28,"minecraft:furnace":3,"minecraft:carrots":100,"minecraft:andesite":4,"minecraft:gold_block":2,"minecraft:potatoes":1,"minecraft:stone":201,"minecraft:redstone_wall_torch":1,"minecraft:oak_slab":2,"minecraft:glass_pane":4,"minecraft:soul_sand":39,"minecraft:basalt":159,"minecraft:oak_fence":1,"minecraft:crafting_table":4,"minecraft:tall_grass":3,"minecraft:lapis_ore":14,"minecraft:diorite":5,"minecraft:sea_pickle":2,"minecraft:spruce_log":25,"minecraft:coal_ore":300,"minecraft:gravel":39,"minecraft:gold_ore":38}},"DataVersion":2584}