{"stats":{"minecraft:custom":{"minecraft:jump":42,"minecraft:open_chest":1,"minecraft:time_since_rest":2494,"minecraft:play_one_minute":2494,"minecraft:damage_taken":120,"minecraft:leave_game":2,"minecraft:sprint_one_cm":9846,"minecraft:time_since_death":2494,"minecraft:walk_on_water_one_cm":2315,"minecraft:walk_one_cm":3820,"minecraft:sneak_time":5,"minecraft:climb_one_cm":843,"minecraft:walk_under_water_one_cm":860,"minecraft:fall_one_cm":1929,"minecraft:fly_one_cm":10859}},"DataVersion":2230}